circ/__init__.py
circ/circ.py
circ/data/mars_mro_ctx_edr_m_c0a/mars_mro_ctx_edr_m_c0a.dbf
circ/data/mars_mro_ctx_edr_m_c0a/mars_mro_ctx_edr_m_c0a.prj
circ/data/mars_mro_ctx_edr_m_c0a/mars_mro_ctx_edr_m_c0a.sbn
circ/data/mars_mro_ctx_edr_m_c0a/mars_mro_ctx_edr_m_c0a.sbx
circ/data/mars_mro_ctx_edr_m_c0a/mars_mro_ctx_edr_m_c0a.shp
circ/data/mars_mro_ctx_edr_m_c0a/mars_mro_ctx_edr_m_c0a.shp.xml
circ/data/mars_mro_ctx_edr_m_c0a/mars_mro_ctx_edr_m_c0a.shx
circ-0.0.1.dist-info/DESCRIPTION.rst
circ-0.0.1.dist-info/METADATA
circ-0.0.1.dist-info/RECORD
circ-0.0.1.dist-info/WHEEL
circ-0.0.1.dist-info/entry_points.txt
circ-0.0.1.dist-info/metadata.json
circ-0.0.1.dist-info/top_level.txt
