Metadata-Version: 2.0
Name: circ
Version: 0.0.1
Summary: A basic CLI to make mosaic vrts using ctx imagery
Home-page: https://github.com/andrewannex/circ
Author: Andrew Annex
Author-email: annex@jhu.edu
License: MIT
Download-URL: https://github.com/AndrewAnnex/circ/archive/0.0.1.tar.gz
Keywords: mars,nasa,ode,pds,cli,tool,ctx,circ,mosaic,gdal
Platform: UNKNOWN
Classifier: Natural Language :: English
Classifier: License :: OSI Approved :: MIT License
Classifier: Development Status :: 3 - Alpha
Classifier: Environment :: Console
Classifier: Intended Audience :: Developers
Classifier: Intended Audience :: Science/Research
Classifier: Programming Language :: Python :: 3 :: Only
Classifier: Programming Language :: Python :: 3.6
Classifier: Topic :: Scientific/Engineering :: Astronomy
Classifier: Topic :: Scientific/Engineering :: GIS
Requires-Dist: requests
Requires-Dist: fire
Requires-Dist: moody
Requires-Dist: geopandas
Requires-Dist: shapely
Requires-Dist: deco
Requires-Dist: sh
Requires-Dist: tqdm
